LICENSE
pixii/__init__.py
pixii/client.py
pixii-0.1.1.dist-info/LICENSE
pixii-0.1.1.dist-info/WHEEL
pixii-0.1.1.dist-info/METADATA
pixii-0.1.1.dist-info/RECORD
