Metadata-Version: 2.1
Name: pixii
Version: 0.1.1
Summary: 
Home-page: https://github.com/k2bd/pixii
License: MIT
Author: Kevin Duff
Author-email: kevinkelduff@gmail.com
Requires-Python: >=3.7,<4.0
Classifier: Development Status :: 1 - Planning
Classifier: Intended Audience :: Developers
Classifier: License :: OSI Approved :: MIT License
Classifier: Operating System :: OS Independent
Classifier: Programming Language :: Python :: 3
Classifier: Programming Language :: Python :: 3 :: Only
Classifier: Programming Language :: Python :: 3.10
Classifier: Programming Language :: Python :: 3.7
Classifier: Programming Language :: Python :: 3.8
Classifier: Programming Language :: Python :: 3.9
Classifier: Topic :: Database
Requires-Dist: aiohttp (>=3.7.4)
Requires-Dist: botocore (>=1.22.7,<2.0.0)
Requires-Dist: pydantic (>=1.8.2,<2.0.0)
Project-URL: Repository, https://github.com/k2bd/pixii
